enumerator.py
num_enumerator-0.0.4.dist-info/LICENSE
num_enumerator-0.0.4.dist-info/METADATA
num_enumerator-0.0.4.dist-info/WHEEL
num_enumerator-0.0.4.dist-info/top_level.txt
num_enumerator-0.0.4.dist-info/RECORD
