Metadata-Version: 2.1
Name: num-enumerator
Version: 0.0.4
Summary: This library helps to manipulate the 2d arrays. User can execute functions like addition, substraction, multiplication and other operations on square matrix and determinant.
Author: Abhineet Raj
Author-email: <abhineetraj01@outlook.com>
Keywords: matrix,determinant,multiplication of matrix,division of matrix,addition of matrix,substraction of matrix,multiplication of determinant,division of determinant,addition of determinant,substraction of determinant
Classifier: Development Status :: 1 - Planning
Classifier: Intended Audience :: Developers
Classifier: Programming Language :: Python :: 3
Classifier: Operating System :: Unix
Classifier: Operating System :: MacOS :: MacOS X
Classifier: Operating System :: Microsoft :: Windows
License-File: LICENSE
